lkinterface/__init__.py
lkinterface/dbProviderInterface.py
lkinterface-0.3.dist-info/METADATA
lkinterface-0.3.dist-info/WHEEL
lkinterface-0.3.dist-info/top_level.txt
lkinterface-0.3.dist-info/RECORD
