Metadata-Version: 2.1
Name: lkinterface
Version: 0.3
Summary: LavKode interfaces
Home-page: https://muthupandian.in
Author: muthugit
Author-email: base.muthupandian@gmail.com
